DotNetLibraryBase/__about__.py
DotNetLibraryBase/__init__.py
DotNetLibraryBase/base.py
DotNetLibraryBase/py.typed
DotNetLibraryBase/runtime/RobotFramework.DotNetLibraryBase.dll
robotframework_dotnetlibrarybase-0.3.0.dist-info/METADATA
robotframework_dotnetlibrarybase-0.3.0.dist-info/WHEEL
robotframework_dotnetlibrarybase-0.3.0.dist-info/licenses/LICENSE.txt
robotframework_dotnetlibrarybase-0.3.0.dist-info/RECORD
