Metadata-Version: 2.4
Name: robotframework-DotNetLibraryBase
Version: 0.3.0
Project-URL: Documentation, https://github.com/imbus/robotframework-dotnetlibrarybase#readme
Project-URL: Issues, https://github.com/unknown/robotframework-dotnetlibrarybase/issues
Project-URL: Source, https://github.com/unknown/robotframework-dotnetlibrarybase
Author-email: Daniel Biehl <daniel.biehl@imbus.de>
License-Expression: Apache-2.0
License-File: LICENSE.txt
Classifier: Development Status :: 4 - Beta
Classifier: Programming Language :: Python
Classifier: Programming Language :: Python :: 3.10
Classifier: Programming Language :: Python :: 3.11
Classifier: Programming Language :: Python :: 3.12
Classifier: Programming Language :: Python :: Implementation :: CPython
Requires-Python: >=3.10
Requires-Dist: pythonnet>=3.0.5
Requires-Dist: robotframework>=6.0
